<MaterialEntry>
	<Key>GreenGlowPod</Key>
	<Pages>
		<Page>
			<Paragraphs>
				<Title>
					<Text>Plante Bioluminescente Verte</Text>
				</Title>
				<Icon>
					<Name>Green GlowPod</Name>
					<Alignment>Center</Alignment>
				</Icon>
				<Paragraph>
					<Text>Cette espèce de flore indigène émet une lueur verte constante en raison d&apos;une réaction chimique juste sous la surface de la plante..</Text>
				</Paragraph>
		
				<Spacer/>
				<Paragraph>
					<Text>Cette plante peut être brûlée pour créer de l&apos;énergie.</Text>
				</Paragraph>
		
			</Paragraphs>
		</Page>
		
	</Pages>
</MaterialEntry>
