<MaterialEntry>
	<Key>PoisonMissileCrafter</Key>
	<Pages>
		<Page>
			<Paragraphs>
				<Title>
					<Text>Assembleur de Missile Mephitic</Text>
				</Title>
				<Icon>
					<Name>Mephitic Missile Assembler</Name>
					<Alignment>Center</Alignment>
				</Icon>
				<Paragraph>
					<Text>Les Cartouches de Chlore utilisées dans la Fabrication de Missiles Imprégnés de Plasma ont un effet additionnel sur la durée des dégâts égal à la moitié des dégâts subis sur 30 secondes.</Text>
				</Paragraph>
				<Paragraph>
					<Text>Cette machine nécessite des trémies contenant au moins une Cartouche de Chlore et un Missile Imprégné de Plasma pour déclencher le processus de toxification.</Text>
				</Paragraph>

				<Header>
					<Text>Caractéristiques</Text>
				</Header>
				<TwoColumnParagraph>
					<Left>Temps de Fabrication:
					Energie Requise:
					Capacité Energie:
					Max. Taux de Recharge:</Left>
					<Right>15 secondes
					8 par seconde
					128
					100 par seconde</Right>
				</TwoColumnParagraph>

			</Paragraphs>
		</Page>
	</Pages>
</MaterialEntry>

